MANIFEST.in
README.md
setup.py
movie_down/__init__.py
movie_down/get_links.py
movie_down/movie_down.py
movie_down/version.py
movie_down.egg-info/PKG-INFO
movie_down.egg-info/SOURCES.txt
movie_down.egg-info/dependency_links.txt
movie_down.egg-info/entry_points.txt
movie_down.egg-info/requires.txt
movie_down.egg-info/top_level.txt