Metadata-Version: 1.1
Name: movie-down
Version: 0.2.0
Summary: Interface to database movie for download
Home-page: https://github.com/Akhail/movie-down
Author: Michel Betancourt
Author-email: MichelBetancourt23@gmail.com
License: MIT
Keywords: movie cli download
Platform: UNKNOWN
Classifier: Development Status :: 4 - Beta
Classifier: License :: OSI Approved :: MIT License
Classifier: Natural Language :: English
Classifier: Operating System :: Unix
Classifier: Programming Language :: Python :: 3.2
Classifier: Programming Language :: Python :: 3.3
Classifier: Programming Language :: Python :: 3.4
Classifier: Operating System :: OS Independent
